MANIFEST.in
setup.cfg
setup.py
rlg/__init__.py
rlg/__main__.py
rlg/mujoco_env.py
rlg.egg-info/PKG-INFO
rlg.egg-info/SOURCES.txt
rlg.egg-info/dependency_links.txt
rlg.egg-info/not-zip-safe
rlg.egg-info/requires.txt
rlg.egg-info/top_level.txt
rlg/agents/__init__.py
rlg/agents/agent.py
rlg/assets/PR2/PR2.xml
rlg/assets/PR2/pr2_arm.xml
rlg/assets/PR2/Meshes/base.stl
rlg/assets/PR2/Meshes/base_L.stl
rlg/assets/PR2/Meshes/caster.stl
rlg/assets/PR2/Meshes/caster_L.stl
rlg/assets/PR2/Meshes/elbow_flex.stl
rlg/assets/PR2/Meshes/finger_tip_l.stl
rlg/assets/PR2/Meshes/finger_tip_pad2_l.stl
rlg/assets/PR2/Meshes/finger_tip_pad2_r.stl
rlg/assets/PR2/Meshes/finger_tip_r.stl
rlg/assets/PR2/Meshes/forearm.stl
rlg/assets/PR2/Meshes/forearm_roll.stl
rlg/assets/PR2/Meshes/forearm_roll_L.stl
rlg/assets/PR2/Meshes/gripper_palm.stl
rlg/assets/PR2/Meshes/head_pan.stl
rlg/assets/PR2/Meshes/head_pan_L.stl
rlg/assets/PR2/Meshes/head_tilt.stl
rlg/assets/PR2/Meshes/head_tilt_L.stl
rlg/assets/PR2/Meshes/hok_tilt.stl
rlg/assets/PR2/Meshes/l_finger.stl
rlg/assets/PR2/Meshes/l_finger_tip.stl
rlg/assets/PR2/Meshes/l_floating.stl
rlg/assets/PR2/Meshes/pr2_wheel.stl
rlg/assets/PR2/Meshes/shoulder_lift.stl
rlg/assets/PR2/Meshes/shoulder_pan.stl
rlg/assets/PR2/Meshes/shoulder_yaw.stl
rlg/assets/PR2/Meshes/tilting_hokuyo.stl
rlg/assets/PR2/Meshes/tilting_hokuyo_L.stl
rlg/assets/PR2/Meshes/torso.stl
rlg/assets/PR2/Meshes/torso_lift.stl
rlg/assets/PR2/Meshes/torso_lift_L.stl
rlg/assets/PR2/Meshes/upper_arm.stl
rlg/assets/PR2/Meshes/upper_arm_roll.stl
rlg/assets/PR2/Meshes/upper_arm_roll_L.stl
rlg/assets/PR2/Meshes/upper_finger_l.stl
rlg/assets/PR2/Meshes/upper_finger_r.stl
rlg/assets/PR2/Meshes/wheel.stl
rlg/assets/PR2/Meshes/wrist_flex.stl
rlg/assets/PR2/Meshes/wrist_roll.stl
rlg/assets/PR2/Meshes/wrist_roll_L.stl
rlg/assets/atlas/atlas.xml
rlg/assets/atlas/meshes_v5/l_clav.stl
rlg/assets/atlas/meshes_v5/l_farm.stl
rlg/assets/atlas/meshes_v5/l_foot.stl
rlg/assets/atlas/meshes_v5/l_hand.stl
rlg/assets/atlas/meshes_v5/l_larm.stl
rlg/assets/atlas/meshes_v5/l_lglut.stl
rlg/assets/atlas/meshes_v5/l_lleg.stl
rlg/assets/atlas/meshes_v5/l_scap.stl
