Metadata-Version: 1.0
Name: rlg
Version: 1.0a0.dev0
Summary: Platform for testing robot RL algorithms
Home-page: http://github.com/ashwinreddy/rlg
Author: Ashwin Reddy
Author-email: 19ashwinr@students.harker.org
License: MIT
Platform: UNKNOWN
